pyghidra/__init__.py
pyghidra/__main__.py
pyghidra/api.py
pyghidra/converters.py
pyghidra/core.py
pyghidra/ghidra_launch.py
pyghidra/ghidradoc.py
pyghidra/gui.py
pyghidra/javac.py
pyghidra/launcher.py
pyghidra/properties.py
pyghidra/script.py
pyghidra/version.py
pyghidra/internal/__init__.py
pyghidra/internal/plugin/__init__.py
pyghidra/internal/plugin/completions.py
pyghidra/internal/plugin/plugin.py
pyghidra-3.0.0.dist-info/LICENSE
pyghidra-3.0.0.dist-info/METADATA
pyghidra-3.0.0.dist-info/WHEEL
pyghidra-3.0.0.dist-info/entry_points.txt
pyghidra-3.0.0.dist-info/top_level.txt
pyghidra-3.0.0.dist-info/RECORD
