Metadata-Version: 2.1
Name: pyghidra
Version: 3.0.0
Summary: Native CPython for Ghidra
Author-email: DC3 <dc3.tsd@us.af.mil>
Maintainer: Ghidra Development Team
Maintainer-email: DC3 <dc3.tsd@us.af.mil>
License: Apache-2.0
Project-URL: Repository, https://github.com/NationalSecurityAgency/ghidra
Keywords: ghidra
Classifier: Development Status :: 5 - Production/Stable
Classifier: Intended Audience :: Developers
Classifier: License :: OSI Approved :: Apache Software License
Classifier: Programming Language :: Python :: 3
Classifier: Programming Language :: Python :: 3.9
Classifier: Programming Language :: Python :: 3.10
Classifier: Programming Language :: Python :: 3.11
Classifier: Programming Language :: Python :: 3.12
Classifier: Programming Language :: Python :: 3.13
Requires-Python: >=3.9
License-File: LICENSE
Requires-Dist: Jpype1==1.5.2
Requires-Dist: packaging
Provides-Extra: testing
Requires-Dist: pytest; extra == "testing"
Requires-Dist: pytest-datadir; extra == "testing"
